django_privates-3.1.1.dist-info/licenses/LICENSE
privates/__init__.py
privates/admin.py
privates/apps.py
privates/fields.py
privates/py.typed
privates/storages.py
privates/test.py
privates/views.py
privates/widgets.py
privates/templates/admin/widgets/clearable_private_file_input.html
django_privates-3.1.1.dist-info/METADATA
django_privates-3.1.1.dist-info/WHEEL
django_privates-3.1.1.dist-info/top_level.txt
django_privates-3.1.1.dist-info/RECORD
