Metadata-Version: 2.4
Name: django-privates
Version: 3.1.1
Summary: Simple private media integration for Django
Author-email: Sergei Maertens <info@regex-it.nl>
License: Copyright (c) 2018 Sergei Maertens <info@regex-it.nl>
Project-URL: Homepage, https://github.com/sergei-maertens/django-privates
Project-URL: Documentation, https://django-privates.readthedocs.io/en/latest/
Project-URL: Bug Tracker, https://github.com/sergei-maertens/django-privates/issues
Project-URL: Source Code, https://github.com/sergei-maertens/django-privates
Keywords: django,media,private,storage
Classifier: Development Status :: 5 - Production/Stable
Classifier: Framework :: Django
Classifier: Framework :: Django :: 4.2
Classifier: Framework :: Django :: 5.2
Classifier: Intended Audience :: Developers
Classifier: Operating System :: Unix
Classifier: Operating System :: MacOS
Classifier: Operating System :: Microsoft :: Windows
Classifier: Programming Language :: Python :: 3.10
Classifier: Programming Language :: Python :: 3.11
Classifier: Programming Language :: Python :: 3.12
Classifier: Programming Language :: Python :: 3.13
Classifier: Topic :: Software Development :: Libraries :: Python Modules
Requires-Python: >=3.10
License-File: LICENSE
Requires-Dist: django>=4.2
Requires-Dist: django-sendfile2>=0.5
Provides-Extra: tests
Requires-Dist: Pillow; extra == "tests"
Requires-Dist: pytest; extra == "tests"
Requires-Dist: pytest-pythonpath; extra == "tests"
Requires-Dist: pytest-django; extra == "tests"
Requires-Dist: pytest-cov; extra == "tests"
Requires-Dist: tox; extra == "tests"
Requires-Dist: pyquery; extra == "tests"
Requires-Dist: ruff; extra == "tests"
Requires-Dist: django-stubs[compatible-mypy]; extra == "tests"
Provides-Extra: docs
Requires-Dist: sphinx; extra == "docs"
Requires-Dist: sphinx-rtd-theme; extra == "docs"
Provides-Extra: release
Requires-Dist: bump-my-version; extra == "release"
Dynamic: license-file
